{
      "api_name": "/bom-node-quantity/findList",
      "table_name": "bomNode用量数量",
      "request": {
        "bomNodeQuantityClazz": "BOM_NODE_QUANTITY"
      },
      "mainTabClazz": "BOM_NODE_QUANTITY",
      "response": {
        "bomNodeQuantityApplicationId": {
          "meaning": "bomNode用量数量应用ID"
        },
        "bomNodeQuantityAuditDate": {
          "meaning": "bomNode用量数量审核时间"
        },
        "bomNodeQuantityAuditStatus": {
          "meaning": "bomNode用量数量审核状态"
        },
        "bomNodeQuantityBizVersion": {
          "meaning": "bomNode用量数量业务自定义版本号"
        },
        "bomNodeQuantityBomNodeQuantityFilterClazz": {
          "meaning": "bomNode用量数量过滤用不对前端开放"
        },
        "bomNodeQuantityBriefName": {
          "meaning": "bomNode用量数量简称"
        },
        "bomNodeQuantityBusDivisId": {
          "meaning": "bomNode用量数量事业部id"
        },
        "bomNodeQuantityClazz": {
          "meaning": "bomNode用量数量子类 类名（表和类一一对应）"
        },
        "bomNodeQuantityComment": {
          "meaning": "bomNode用量数量评论"
        },
        "bomNodeQuantityCorrPaper": {
          "meaning": "bomNode用量数量楞别"
        },
        "bomNodeQuantityCreateTime": {
          "meaning": "bomNode用量数量创建时间"
        },
        "bomNodeQuantityCreator": {
          "meaning": "bomNode用量数量创建人"
        },
        "bomNodeQuantityCreatorId": {
          "meaning": "bomNode用量数量创建人ID"
        },
        "bomNodeQuantityDateExtra1": {
          "meaning": "bomNode用量数量扩展时间1"
        },
        "bomNodeQuantityDateExtra2": {
          "meaning": "bomNode用量数量扩展时间2"
        },
        "bomNodeQuantityDateExtra3": {
          "meaning": "bomNode用量数量扩展时间3"
        },
        "bomNodeQuantityDateExtra4": {
          "meaning": "bomNode用量数量扩展时间4"
        },
        "bomNodeQuantityDateExtra5": {
          "meaning": "bomNode用量数量扩展时间5"
        },
        "bomNodeQuantityDefaultType": {
          "meaning": "bomNode用量数量智能节点主类型 默认类型（类型的system_code字段）"
        },
        "bomNodeQuantityDescription": {
          "meaning": "bomNode用量数量描述"
        },
        "bomNodeQuantityEngName": {
          "meaning": "bomNode用量数量英文名称"
        },
        "bomNodeQuantityExtension": {
          "meaning": "bomNode用量数量扩展数据"
        },
        "bomNodeQuantityExternalState": {
          "meaning": "bomNode用量数量上流程状态位。0-未开始；1-进行中；2-异常；3-结束；4-中止；5-关闭"
        },
        "bomNodeQuantityFilterClazz": {
          "meaning": "bomNode用量数量过滤用不对前端开放"
        },
        "bomNodeQuantityFlags": {
          "meaning": "bomNode用量数量63位标志位"
        },
        "bomNodeQuantityFromAuditDate": {
          "meaning": "bomNodeQuantityFromAuditDate"
        },
        "bomNodeQuantityFromCreateTime": {
          "meaning": "bomNodeQuantityFromCreateTime"
        },
        "bomNodeQuantityFromDateExtra1": {
          "meaning": "bomNodeQuantityFromDateExtra1"
        },
        "bomNodeQuantityFromDateExtra2": {
          "meaning": "bomNodeQuantityFromDateExtra2"
        },
        "bomNodeQuantityFromDateExtra3": {
          "meaning": "bomNodeQuantityFromDateExtra3"
        },
        "bomNodeQuantityFromDateExtra4": {
          "meaning": "bomNodeQuantityFromDateExtra4"
        },
        "bomNodeQuantityFromDateExtra5": {
          "meaning": "bomNodeQuantityFromDateExtra5"
        },
        "bomNodeQuantityFromUpdateTime": {
          "meaning": "bomNodeQuantityFromUpdateTime"
        },
        "bomNodeQuantityGroovyScript": {
          "meaning": "bomNode用量数量groovy脚本"
        },
        "bomNodeQuantityGropeCode": {
          "meaning": "bomNode用量数量搜索码"
        },
        "bomNodeQuantityId": {
          "meaning": "bomNode用量数量PK",
          "is_primary": true
        },
        "bomNodeQuantityInUsed": {
          "meaning": "bomNode用量数量是否被使用"
        },
        "bomNodeQuantityIsBanned": {
          "meaning": "bomNode用量数量是否被禁用"
        },
        "bomNodeQuantityIsDeleted": {
          "meaning": "bomNode用量数量是否被删除"
        },
        "bomNodeQuantityIsMainFlow": {
          "meaning": "bomNode用量数量是否是主流程"
        },
        "bomNodeQuantityIsolation": {
          "meaning": "bomNode用量数量智能节点数据隔离标识"
        },
        "bomNodeQuantityJsScript": {
          "meaning": "bomNode用量数量js脚本"
        },
        "bomNodeQuantityLevel": {
          "meaning": "bomNode用量数量层级"
        },
        "bomNodeQuantityName": {
          "meaning": "bomNode用量数量智能节点名"
        },
        "bomNodeQuantityNameCodeSearch": {
          "meaning": "bomNode用量数量name、user_code模糊搜索"
        },
        "bomNodeQuantityNumberExtra1": {
          "meaning": "bomNode用量数量扩展数量1"
        },
        "bomNodeQuantityNumberExtra2": {
          "meaning": "bomNode用量数量扩展数量2"
        },
        "bomNodeQuantityNumberExtra3": {
          "meaning": "bomNode用量数量扩展数量3"
        },
        "bomNodeQuantityNumberExtra4": {
          "meaning": "bomNode用量数量扩展数量4"
        },
        "bomNodeQuantityNumberExtra5": {
          "meaning": "bomNode用量数量扩展数量5"
        },
        "bomNodeQuantityOutputModulus": {
          "meaning": "bomNode用量数量产出模数"
        },
        "bomNodeQuantityOutputPercent": {
          "meaning": "bomNode用量数量产出比"
        },
        "bomNodeQuantityParentId": {
          "meaning": "bomNode用量数量父节点ID"
        },
        "bomNodeQuantityPrdIApyQuantity": {
          "meaning": "bomNode用量数量已开入库申请数量"
        },
        "bomNodeQuantityPrdIApyStatus": {
          "meaning": "bomNode用量数量已开入库申请状态"
        },
        "bomNodeQuantityProcessInstanceId": {
          "meaning": "bomNode用量数量流程实例ID"
        },
        "bomNodeQuantityPurOrOutQuantity": {
          "meaning": "bomNode用量数量已采购 / 外发数量"
        },
        "bomNodeQuantityPurOrOutStatus": {
          "meaning": "bomNode用量数量已采购 / 外发状态"
        },
        "bomNodeQuantityQuantity": {
          "meaning": "bomNode用量数量数量"
        },
        "bomNodeQuantitySerialNumber": {
          "meaning": "bomNode用量数量顺序号"
        },
        "bomNodeQuantityShippedQuantity": {
          "meaning": "bomNode用量数量已出库数量"
        },
        "bomNodeQuantityShippedStatus": {
          "meaning": "bomNode用量数量已出库状态"
        },
        "bomNodeQuantitySource": {
          "meaning": "bomNode用量数量源节点id"
        },
        "bomNodeQuantitySourceVersion": {
          "meaning": "bomNode用量数量源节点版本"
        },
        "bomNodeQuantityState": {
          "meaning": "bomNode用量数量通用状态"
        },
        "bomNodeQuantityStoredQuantity": {
          "meaning": "bomNode用量数量已入库数量"
        },
        "bomNodeQuantityStoredStatus": {
          "meaning": "bomNode用量数量已入库状态"
        },
        "bomNodeQuantitySystemCode": {
          "meaning": "bomNode用量数量系统编码"
        },
        "bomNodeQuantityTarget": {
          "meaning": "bomNode用量数量目标节点id"
        },
        "bomNodeQuantityTargetVersion": {
          "meaning": "bomNode用量数量目标节点版本"
        },
        "bomNodeQuantityTaskNodeName": {
          "meaning": "bomNode用量数量任务节点名称"
        },
        "bomNodeQuantityThirdPartyClass": {
          "meaning": "bomNode用量数量第三方分类"
        },
        "bomNodeQuantityThirdPartyId": {
          "meaning": "bomNode用量数量第三方系统中的唯一ID"
        },
        "bomNodeQuantityThirdPartyName": {
          "meaning": "bomNode用量数量第三方名称"
        },
        "bomNodeQuantityToAuditDate": {
          "meaning": "bomNodeQuantityToAuditDate"
        },
        "bomNodeQuantityToCreateTime": {
          "meaning": "bomNodeQuantityToCreateTime"
        },
        "bomNodeQuantityToDateExtra1": {
          "meaning": "bomNodeQuantityToDateExtra1"
        },
        "bomNodeQuantityToDateExtra2": {
          "meaning": "bomNodeQuantityToDateExtra2"
        },
        "bomNodeQuantityToDateExtra3": {
          "meaning": "bomNodeQuantityToDateExtra3"
        },
        "bomNodeQuantityToDateExtra4": {
          "meaning": "bomNodeQuantityToDateExtra4"
        },
        "bomNodeQuantityToDateExtra5": {
          "meaning": "bomNodeQuantityToDateExtra5"
        },
        "bomNodeQuantityToUpdateTime": {
          "meaning": "bomNodeQuantityToUpdateTime"
        },
        "bomNodeQuantityTypeCode": {
          "meaning": "bomNode用量数量连接类型"
        },
        "bomNodeQuantityUpdateTime": {
          "meaning": "bomNode用量数量更新时间"
        },
        "bomNodeQuantityUpdater": {
          "meaning": "bomNode用量数量更新人"
        },
        "bomNodeQuantityUpdaterId": {
          "meaning": "bomNode用量数量更新人ID"
        },
        "bomNodeQuantityUseRate": {
          "meaning": "bomNode用量数量使用率"
        },
        "bomNodeQuantityUserCode": {
          "meaning": "bomNode用量数量智能节点的唯一编码"
        },
        "bomNodeQuantityValue": {
          "meaning": "bomNode用量数量连接权值"
        },
        "bomNodeQuantityVarExtra1": {
          "meaning": "bomNode用量数量扩展1"
        },
        "bomNodeQuantityVarExtra2": {
          "meaning": "bomNode用量数量扩展2"
        },
        "bomNodeQuantityVarExtra3": {
          "meaning": "bomNode用量数量扩展3"
        },
        "bomNodeQuantityVarExtra4": {
          "meaning": "bomNode用量数量扩展4"
        },
        "bomNodeQuantityVarExtra5": {
          "meaning": "bomNode用量数量扩展5"
        },
        "bomNodeQuantityVersion": {
          "meaning": "bomNode用量数量版本号"
        }
      }
    }